{"1": "Caries", "3": "Caries", "4": "Caries", "6": "Restoration", "7": "Restoration", "8": "Caries", "9": "Enamel", "11": "Enamel", "12": "Enamel", "13": "Pulp", "14": "Pulp", "15": "Pulp", "16": "Pulp", "17": "Dentin", "20": "Dentin", "21": "Mandibular_alveolar_nerve", "23": "Background", "24": "Background", "27": "Enamel", "28": "Dentin", "29": "Restoration", "30": "Enamel", "31": "Enamel", "32": "Enamel", "33": "Dentin", "34": "Mandibular_alveolar_nerve", "35": "Alveolar_bone", "36": "Dentin"}